protocol0/__init__.py
protocol0/application/__init__.py
protocol0/application/command/__init__.py
protocol0/application/command/BounceTrackToAudioCommand.py
protocol0/application/command/CheckAudioExportValidCommand.py
protocol0/application/command/DrumRackToSimplerCommand.py
protocol0/application/command/EmitBackendEventCommand.py
protocol0/application/command/FireSceneToPositionCommand.py
protocol0/application/command/FireSelectedSceneCommand.py
protocol0/application/command/GetSetStateCommand.py
protocol0/application/command/GoToGroupTrackCommand.py
protocol0/application/command/LoadDeviceCommand.py
protocol0/application/command/LoadDrumRackCommand.py
protocol0/application/command/LoadMatchingTrackCommand.py
protocol0/application/command/LoadMinitaurCommand.py
protocol0/application/command/LoadRev2Command.py
protocol0/application/command/MidiNoteCommand.py
protocol0/application/command/PlayPauseSongCommand.py
protocol0/application/command/RecordUnlimitedCommand.py
protocol0/application/command/ReloadScriptCommand.py
protocol0/application/command/ResetPlaybackCommand.py
protocol0/application/command/ScrollScenePositionCommand.py
protocol0/application/command/ScrollScenesCommand.py
protocol0/application/command/ScrollSceneTracksCommand.py
protocol0/application/command/ScrollTrackVolumeCommand.py
protocol0/application/command/SelectOrLoadDeviceCommand.py
protocol0/application/command/SelectTrackCommand.py
protocol0/application/command/SerializableCommand.py
protocol0/application/command/ShowAutomationCommand.py
protocol0/application/command/ShowInstrumentCommand.py
protocol0/application/command/ShowMessageCommand.py
protocol0/application/command/ToggleArmCommand.py
protocol0/application/command/ToggleNotesCommand.py
protocol0/application/command/ToggleReferenceTrackCommand.py
protocol0/application/command/ToggleSceneLoopCommand.py
protocol0/application/command/UnfoldSelectedSceneCommand.py
protocol0/application/command_handler/__init__.py
protocol0-1.0.15.dist-info/LICENSE.md
protocol0-1.0.15.dist-info/METADATA
protocol0-1.0.15.dist-info/WHEEL
protocol0-1.0.15.dist-info/RECORD
