Metadata-Version: 2.1
Name: protocol0
Version: 1.0.15
Summary: Protocol0 ableton remote script
Home-page: https://github.com/lebrunthibault/protocol0
License: MIT
Keywords: remote script,ableton
Author: Thibault Lebrun
Author-email: thibaultlebrun@live.fr
Requires-Python: >=3.7.3
Classifier: Development Status :: 4 - Beta
Classifier: License :: OSI Approved :: MIT License
Classifier: Programming Language :: Python
Classifier: Programming Language :: Python :: 3
Classifier: Programming Language :: Python :: 3.8
Classifier: Programming Language :: Python :: 3.9
Classifier: Programming Language :: Python :: 3.10
Classifier: Programming Language :: Python :: 3.11
Classifier: Programming Language :: Python :: 3.7
Requires-Dist: loguru (>=0.7.0,<0.8.0)
Requires-Dist: qualname (>=0.1.0,<0.2.0)
Requires-Dist: typing-extensions (>=4.6.3,<5.0.0)
Project-URL: Repository, https://github.com/lebrunthibault/protocol0
